<?xml version="1.0"?>
<!--<!DOCTYPE metadata SYSTEM "http://www.esri.com/metadata/esriprof80.dtd">-->
<metadata xml:lang="en"><Esri><CreaDate>20071029</CreaDate><CreaTime>14461600</CreaTime><SyncDate>20080623</SyncDate><SyncTime>12015100</SyncTime><ModDate>20080623</ModDate><ModTime>12015100</ModTime><SyncOnce>FALSE</SyncOnce><MetaID>{3DDEE0EE-0FFA-439F-B481-590C1D972E0A}</MetaID><DataProperties><lineage><Process Name="PolygonToLine_1" ToolSource="C:\Program Files\ArcGIS\ArcToolbox\Toolboxes\Data Management Tools.tbx\PolygonToLine" Date="20080328" Time="151009">PolygonToLine C:\arcdata_server\watersheds.gdb\drb_bnd_polygon C:\arcdata_server\watersheds.gdb\drb_bnd_line</Process><Process ToolSource="C:\Program Files\ArcGIS\ArcToolbox\Toolboxes\Data Management Tools.tbx\CopyFeatures" Date="20080623" Time="120151">CopyFeatures C:\arcdata_server\watersheds.gdb\drb_bnd_arc "C:\GIS Information\UTM_Shapefiles\drb_bnd_arc.shp" # 0 0 0</Process></lineage></DataProperties></Esri><idinfo><native Sync="TRUE">Microsoft Windows XP Version 5.1 (Build 2600) Service Pack 2; ESRI ArcCatalog 9.2.5.1450</native><descript><langdata Sync="TRUE">en</langdata><abstract>This data set was created by the Delaware River Basin Commission for use in their GIS for planning and mapping purposes.</abstract><purpose>For use at 1:24,000 scale</purpose></descript><citation><citeinfo><origin>DRBC</origin><pubdate>2001</pubdate><title>Delaware River Watershed Boundary</title><ftname Sync="TRUE">drb_bnd_arc</ftname><geoform Sync="TRUE">vector digital data</geoform><onlink Sync="TRUE">\\KAREN-DELL\C$\GIS Information\UTM_Shapefiles\drb_bnd_arc.shp</onlink></citeinfo></citation><timeperd><current>publication date</current><timeinfo><sngdate><caldate>2001</caldate></sngdate></timeinfo></timeperd><status><progress>Complete</progress><update>None planned</update></status><spdom><bounding><westbc Sync="TRUE">-76.440848</westbc><eastbc Sync="TRUE">-74.349910</eastbc><northbc Sync="TRUE">42.463152</northbc><southbc Sync="TRUE">38.683167</southbc></bounding><lboundng><leftbc Sync="TRUE">381523.374974</leftbc><rightbc Sync="TRUE">553448.375026</rightbc><bottombc Sync="TRUE">4282498.500032</bottombc><topbc Sync="TRUE">4701201.499968</topbc></lboundng></spdom><keywords><theme><themekt>None</themekt><themekey>watershed</themekey><themekey>estuary</themekey><themekey>sub basin</themekey></theme><place><placekey>Delaware River</placekey><placekey>Delaware</placekey><placekey>Pennsylvania</placekey><placekey>New York</placekey><placekey>New Jersey</placekey><placekey>Delaware Bay</placekey></place></keywords><accconst>None</accconst><useconst>None</useconst><natvform Sync="TRUE">Shapefile</natvform><ptcontac><cntinfo><cntorgp><cntorg>Delaware River Basin Commission</cntorg><cntper>Karen Reavy</cntper></cntorgp><cntpos>GIS Coordinator</cntpos><cntaddr><addrtype>mailing and physical address</addrtype><address>PO Box 7360
25 State Police Drive
</address><city>West Trenton</city><state>NJ</state><postal>08628-0360</postal></cntaddr><cntvoice>609-883-9500</cntvoice><cntfax>609-883-9522</cntfax><cntemail>kreavy@drbc.state.nj.us</cntemail></cntinfo></ptcontac><secinfo><secclass>Unclassified</secclass></secinfo></idinfo><metainfo><langmeta Sync="TRUE">en</langmeta><metstdn Sync="TRUE">FGDC Content Standards for Digital Geospatial Metadata</metstdn><metstdv Sync="TRUE">FGDC-STD-001-1998</metstdv><mettc Sync="TRUE">local time</mettc><metc><cntinfo><cntorgp><cntper>Karen Reavy</cntper><cntorg>Delaware River Basin Commision</cntorg></cntorgp><cntaddr><addrtype>mailing and physical address</addrtype><city>West Trenton</city><state>NJ</state><postal>08628-0360</postal><address>PO BOX 7360
25 State Police Drive</address></cntaddr><cntvoice>609-883-9500</cntvoice><cntfax>609-883-9522</cntfax><cntemail>kreavy@drbc.state.nj.us</cntemail></cntinfo></metc><metd>20010312</metd><metextns><onlink Sync="TRUE">http://www.esri.com/metadata/esriprof80.html</onlink><metprof Sync="TRUE">ESRI Metadata Profile</metprof></metextns></metainfo><spdoinfo><direct Sync="TRUE">Vector</direct><ptvctinf><esriterm Name="drb_bnd_arc"><efeatyp Sync="TRUE">Simple</efeatyp><efeageom Sync="TRUE">Polyline</efeageom><esritopo Sync="TRUE">FALSE</esritopo><efeacnt Sync="TRUE">0</efeacnt><spindex Sync="TRUE">FALSE</spindex><linrefer Sync="TRUE">FALSE</linrefer></esriterm><sdtsterm Name="drb_bnd_arc"><sdtstype Sync="TRUE">String</sdtstype><ptvctcnt Sync="TRUE">0</ptvctcnt></sdtsterm><esriterm Name="label"><efeatyp Sync="TRUE">Simple</efeatyp><efeageom Sync="TRUE">Label</efeageom><esritopo Sync="TRUE">FALSE</esritopo><efeacnt Sync="TRUE">1</efeacnt><spindex Sync="TRUE">TRUE</spindex><linrefer Sync="TRUE">FALSE</linrefer></esriterm><sdtsterm Name="label"><sdtstype Sync="TRUE">Label point</sdtstype><ptvctcnt Sync="TRUE">1</ptvctcnt></sdtsterm><esriterm Name="polygon"><efeatyp Sync="TRUE">Simple</efeatyp><efeageom Sync="TRUE">Polygon</efeageom><esritopo Sync="TRUE">TRUE</esritopo><efeacnt Sync="TRUE">1</efeacnt><spindex Sync="TRUE">TRUE</spindex><linrefer Sync="TRUE">FALSE</linrefer></esriterm><sdtsterm Name="polygon"><sdtstype Sync="TRUE">GT-polygon composed of chains</sdtstype><ptvctcnt Sync="TRUE">1</ptvctcnt></sdtsterm><esriterm Name="tic"><efeatyp Sync="TRUE">Simple</efeatyp><efeageom Sync="TRUE">Tic</efeageom><esritopo Sync="TRUE">FALSE</esritopo><efeacnt Sync="TRUE">14</efeacnt><spindex Sync="TRUE">FALSE</spindex><linrefer Sync="TRUE">FALSE</linrefer></esriterm><sdtsterm Name="tic"><sdtstype Sync="TRUE">Point</sdtstype><ptvctcnt Sync="TRUE">14</ptvctcnt></sdtsterm></ptvctinf></spdoinfo><spref><horizsys><cordsysn><geogcsn Sync="TRUE">GCS_North_American_1983</geogcsn><projcsn Sync="TRUE">NAD_1983_UTM_Zone_18N</projcsn></cordsysn><planar><planci><plance Sync="TRUE">coordinate pair</plance><plandu Sync="TRUE">meters</plandu><coordrep><absres Sync="TRUE">0.000000</absres><ordres Sync="TRUE">0.000000</ordres></coordrep></planci><gridsys><gridsysn Sync="TRUE">Universal Transverse Mercator</gridsysn><utm><utmzone Sync="TRUE">18</utmzone><transmer><sfctrmer Sync="TRUE">0.999600</sfctrmer><longcm Sync="TRUE">-75.000000</longcm><latprjo Sync="TRUE">0.000000</latprjo><feast Sync="TRUE">500000.000000</feast><fnorth Sync="TRUE">0.000000</fnorth></transmer></utm></gridsys></planar><geodetic><horizdn Sync="TRUE">North American Datum of 1983</horizdn><ellips Sync="TRUE">Geodetic Reference System 80</ellips><semiaxis Sync="TRUE">6378137.000000</semiaxis><denflat Sync="TRUE">298.257222</denflat></geodetic></horizsys></spref><eainfo><detailed Name="drb_bnd_arc"><attr><attrlabl Sync="TRUE">Shape</attrlabl><attwidth Sync="TRUE">0</attwidth><atoutwid Sync="TRUE">5</atoutwid><attrtype Sync="TRUE">Geometry</attrtype><attrdef Sync="TRUE">Feature geometry.</attrdef><attrdefs Sync="TRUE">ESRI</attrdefs><attrdomv><udom Sync="TRUE">Coordinates defining the features.</udom></attrdomv><attalias Sync="TRUE">Shape</attalias><atprecis Sync="TRUE">0</atprecis><attscale Sync="TRUE">0</attscale></attr><enttyp><enttypl Sync="TRUE">drb_bnd_arc</enttypl><enttypt Sync="TRUE">Feature Class</enttypt><enttypc Sync="TRUE">0</enttypc></enttyp><attr><attrlabl Sync="TRUE">LEFT_FID</attrlabl><attalias Sync="TRUE">LEFT_FID</attalias><attrtype Sync="TRUE">Integer</attrtype><attwidth Sync="TRUE">4</attwidth><atprecis Sync="TRUE">0</atprecis><attscale Sync="TRUE">0</attscale></attr><attr><attrlabl Sync="TRUE">RIGHT_FID</attrlabl><attalias Sync="TRUE">RIGHT_FID</attalias><attrtype Sync="TRUE">Number</attrtype><attwidth Sync="TRUE">9</attwidth></attr><attr><attrlabl Sync="TRUE">FID</attrlabl><attalias Sync="TRUE">FID</attalias><attrtype Sync="TRUE">Number</attrtype><attwidth Sync="TRUE">9</attwidth><attrdef Sync="TRUE">Internal feature number.</attrdef><attrdefs Sync="TRUE">ESRI</attrdefs><attrdomv><udom Sync="TRUE">Sequential unique whole numbers that are automatically generated.</udom></attrdomv></attr><attr><attrlabl Sync="TRUE">Shape_Leng</attrlabl><attalias Sync="TRUE">Shape_Leng</attalias><attrtype Sync="TRUE">Float</attrtype><attwidth Sync="TRUE">19</attwidth><atnumdec Sync="TRUE">11</atnumdec></attr></detailed><detailed Name="drb_bnd.pat"><enttyp><enttypl Sync="TRUE">drb_bnd.pat</enttypl><enttypt Sync="TRUE">Feature Class</enttypt><enttypc Sync="TRUE">1</enttypc></enttyp><attr><attrlabl Sync="TRUE">FID</attrlabl><attwidth Sync="TRUE">4</attwidth><atoutwid Sync="TRUE">5</atoutwid><attrtype Sync="TRUE">OID</attrtype><attalias Sync="TRUE">FID</attalias><atprecis Sync="TRUE">0</atprecis><attscale Sync="TRUE">0</attscale><attrdef Sync="TRUE">Internal feature number.</attrdef><attrdefs Sync="TRUE">ESRI</attrdefs><attrdomv><udom Sync="TRUE">Sequential unique whole numbers that are automatically generated.</udom></attrdomv></attr><attr><attrlabl Sync="TRUE">Shape</attrlabl><attwidth Sync="TRUE">0</attwidth><atoutwid Sync="TRUE">5</atoutwid><attrtype Sync="TRUE">Geometry</attrtype><attalias Sync="TRUE">Shape</attalias><atprecis Sync="TRUE">0</atprecis><attscale Sync="TRUE">0</attscale><attrdef Sync="TRUE">Feature geometry.</attrdef><attrdefs Sync="TRUE">ESRI</attrdefs><attrdomv><udom Sync="TRUE">Coordinates defining the features.</udom></attrdomv></attr><attr><attrlabl Sync="TRUE">AREA</attrlabl><attwidth Sync="TRUE">9</attwidth><atoutwid Sync="TRUE">12</atoutwid><attrtype Sync="TRUE">Number</attrtype><attrdef Sync="TRUE">Area of feature in internal units squared.</attrdef><attrdefs Sync="TRUE">ESRI</attrdefs><attrdomv><udom Sync="TRUE">Positive real numbers that are automatically generated.</udom></attrdomv></attr><attr><attrlabl Sync="TRUE">PERIMETER</attrlabl><attwidth Sync="TRUE">9</attwidth><atoutwid Sync="TRUE">12</atoutwid><attrtype Sync="TRUE">Number</attrtype><attrdef Sync="TRUE">Perimeter of feature in internal units.</attrdef><attrdefs Sync="TRUE">ESRI</attrdefs><attrdomv><udom Sync="TRUE">Positive real numbers that are automatically generated.</udom></attrdomv></attr><attr><attrlabl Sync="TRUE">DRB_BND#</attrlabl><attwidth Sync="TRUE">19</attwidth><atoutwid Sync="TRUE">5</atoutwid><attrtype Sync="TRUE">Float</attrtype><attrdef Sync="TRUE">Internal feature number.</attrdef><attrdefs Sync="TRUE">ESRI</attrdefs><attrdomv><udom Sync="TRUE">Sequential unique whole numbers that are automatically generated.</udom></attrdomv><atnumdec Sync="TRUE">11</atnumdec></attr><attr><attrlabl Sync="TRUE">DRB_BND-ID</attrlabl><attwidth Sync="TRUE">4</attwidth><atoutwid Sync="TRUE">5</atoutwid><attrtype Sync="TRUE">Binary</attrtype><attrdef Sync="TRUE">User-defined feature number.</attrdef><attrdefs Sync="TRUE">ESRI</attrdefs></attr><attr><attrlabl Sync="TRUE">SQMI</attrlabl><attwidth Sync="TRUE">5</attwidth><atoutwid Sync="TRUE">5</atoutwid><attrtype Sync="TRUE">Integer</attrtype><attrdef>Area in Square Miles</attrdef></attr><attr><attrlabl Sync="TRUE">NAME</attrlabl><attwidth Sync="TRUE">50</attwidth><atoutwid Sync="TRUE">50</atoutwid><attrtype Sync="TRUE">Character</attrtype></attr></detailed></eainfo><distinfo><stdorder><digform><digtinfo><formname Sync="TRUE">ARC</formname><filedec Sync="TRUE">No compression applied</filedec><transize Sync="TRUE">0.000</transize><dssize Sync="TRUE">0.000</dssize></digtinfo><digtopt><onlinopt><accinstr Sync="TRUE">Local area network</accinstr><computer><networka><networkr Sync="TRUE">\\KAREN\l\drbc\covers\drb_bnd</networkr></networka></computer></onlinopt></digtopt></digform></stdorder><resdesc Sync="TRUE">Downloadable Data</resdesc></distinfo><dataIdInfo><envirDesc Sync="TRUE">Microsoft Windows XP Version 5.1 (Build 2600) Service Pack 2; ESRI ArcCatalog 9.2.5.1450</envirDesc><dataLang><languageCode Sync="TRUE" value="en"></languageCode></dataLang><idCitation><resTitle Sync="TRUE">drb_bnd_arc</resTitle><presForm><PresFormCd Sync="TRUE" value="005"></PresFormCd></presForm></idCitation><spatRpType><SpatRepTypCd Sync="TRUE" value="001"></SpatRepTypCd></spatRpType><geoBox esriExtentType="decdegrees"><westBL Sync="TRUE">-76.440848</westBL><eastBL Sync="TRUE">-74.34991</eastBL><northBL Sync="TRUE">42.463152</northBL><southBL Sync="TRUE">38.683167</southBL><exTypeCode Sync="TRUE">1</exTypeCode></geoBox><dataExt><geoEle><GeoBndBox esriExtentType="native"><westBL Sync="TRUE">381523.374974</westBL><eastBL Sync="TRUE">553448.375026</eastBL><northBL Sync="TRUE">4701201.499968</northBL><southBL Sync="TRUE">4282498.500032</southBL><exTypeCode Sync="TRUE">1</exTypeCode></GeoBndBox></geoEle></dataExt></dataIdInfo><mdLang><languageCode Sync="TRUE" value="en"></languageCode></mdLang><mdStanName Sync="TRUE">ISO 19115 Geographic Information - Metadata</mdStanName><mdStanVer Sync="TRUE">DIS_ESRI1.0</mdStanVer><mdChar><CharSetCd Sync="TRUE" value="004"></CharSetCd></mdChar><mdHrLv><ScopeCd Sync="TRUE" value="005"></ScopeCd></mdHrLv><mdHrLvName Sync="TRUE">dataset</mdHrLvName><distInfo><distributor><distorTran><onLineSrc><orDesc Sync="TRUE">002</orDesc><linkage Sync="TRUE">file://\\KAREN-DELL\C$\GIS Information\UTM_Shapefiles\drb_bnd_arc.shp</linkage><protocol Sync="TRUE">Local Area Network</protocol></onLineSrc><transSize Sync="TRUE">0.000</transSize></distorTran><distorFormat><formatName Sync="TRUE">Shapefile</formatName></distorFormat></distributor></distInfo><refSysInfo><RefSystem><refSysID><identCode Sync="TRUE">NAD_1983_UTM_Zone_18N</identCode></refSysID></RefSystem></refSysInfo><spatRepInfo><VectSpatRep><topLvl><TopoLevCd Sync="TRUE" value="001"></TopoLevCd></topLvl><geometObjs Name="drb_bnd_arc"><geoObjTyp><GeoObjTypCd Sync="TRUE" value="001"></GeoObjTypCd></geoObjTyp><geoObjCnt Sync="TRUE">0</geoObjCnt></geometObjs></VectSpatRep></spatRepInfo><mdDateSt Sync="TRUE">20080623</mdDateSt><dataqual><lineage><procstep><procdesc Sync="TRUE">Dataset copied.</procdesc><srcused Sync="TRUE"></srcused><date Sync="TRUE">20021106</date><time Sync="TRUE">09565900</time></procstep><procstep><procdesc Sync="TRUE">Dataset copied.</procdesc><srcused Sync="TRUE">\\KAREN-DELL\C$\arcdata\drbc\GDB\drb.mdb</srcused><date Sync="TRUE">20071029</date><time Sync="TRUE">14461600</time></procstep></lineage></dataqual></metadata>
